pymatriz/__init__.py
pymatriz/client.py
pymatriz/client_interface.py
pymatriz/enums.py
pymatriz/exceptions.py
pymatriz/globals.py
pymatriz/messages.py
pymatriz/parser.py
pymatriz/rest_client.py
pymatriz/urls.py
pymatriz/utils.py
pymatriz/websocket_client.py
pymatriz-0.1.4.dist-info/LICENSE
pymatriz-0.1.4.dist-info/METADATA
pymatriz-0.1.4.dist-info/WHEEL
pymatriz-0.1.4.dist-info/top_level.txt
pymatriz-0.1.4.dist-info/RECORD
